odoo10_addon_sale_order_priority-10.0.1.0.1-py3.8-nspkg.pth
odoo/addons/sale_order_priority/README.rst
odoo/addons/sale_order_priority/__init__.py
odoo/addons/sale_order_priority/__manifest__.py
odoo/addons/sale_order_priority/i18n/ca.po
odoo/addons/sale_order_priority/i18n/es.po
odoo/addons/sale_order_priority/i18n/it.po
odoo/addons/sale_order_priority/i18n/sale_order_priority.pot
odoo/addons/sale_order_priority/models/__init__.py
odoo/addons/sale_order_priority/models/sale.py
odoo/addons/sale_order_priority/static/description/icon.png
odoo/addons/sale_order_priority/tests/__init__.py
odoo/addons/sale_order_priority/tests/test_sale_stock.py
odoo/addons/sale_order_priority/views/sale.xml
odoo10_addon_sale_order_priority-10.0.1.0.1.dist-info/METADATA
odoo10_addon_sale_order_priority-10.0.1.0.1.dist-info/WHEEL
odoo10_addon_sale_order_priority-10.0.1.0.1.dist-info/namespace_packages.txt
odoo10_addon_sale_order_priority-10.0.1.0.1.dist-info/top_level.txt
odoo10_addon_sale_order_priority-10.0.1.0.1.dist-info/RECORD
